LICENSE
README.md
pyproject.toml
setup.py
deps/requirements.in
src/biotest/__init__.py
src/biotest/_version.py
src/biotest/compare_files.py
src/biotest.egg-info/PKG-INFO
src/biotest.egg-info/SOURCES.txt
src/biotest.egg-info/dependency_links.txt
src/biotest.egg-info/entry_points.txt
src/biotest.egg-info/requires.txt
src/biotest.egg-info/top_level.txt
src/biotest/cli/__init__.py
src/biotest/cli/main.py