Metadata-Version: 2.1
Name: biotest
Version: 0.0.4
Summary: Compare PDB files with a reasonable tolerance
Author: Kiyoon Kim
License:                                  Apache License
Project-URL: Homepage, https://github.com/deargen/biotest
Keywords: development,template
Classifier: Programming Language :: Python :: Implementation :: CPython
Classifier: Programming Language :: Python
Classifier: Programming Language :: Python :: 3
Classifier: Programming Language :: Python :: 3.10
Classifier: Programming Language :: Python :: 3.11
Classifier: Programming Language :: Python :: 3.12
Classifier: Programming Language :: Python :: 3.13
Classifier: License :: OSI Approved :: Apache Software License
Requires-Python: <4,>=3.10
Requires-Dist: rich>=13.0.0
Requires-Dist: typer>=0.12.4
Requires-Dist: numpy
